Workbook

Sheet DCF
A3: $ millions | B3: FY2025A | C3: FY2026E | D3: FY2027E | E3: FY2028E | F3: FY2029E | G3: FY2030E
A4: Revenue growth | B4: =Inputs!D4/Inputs!C4-1 -> 0.064255118 | C4: 0.06 | D4: 0.055 | E4: 0.05 | F4: 0.045 | G4: 0.04
A5: Revenue | B5: =Inputs!D4 -> 416161 | C5: =B5*(1+C4) -> 441130.66 | D5: =C5*(1+D4) -> 465392.85 | E5: =D5*(1+E4) -> 488662.49 | F5: =E5*(1+F4) -> 510652.3 | G5: =F5*(1+G4) -> 531078.39
A6: EBIT margin | B6: =Inputs!D5/Inputs!D4 -> 0.319708 | C6: 0.32 | D6: 0.32 | E6: 0.32 | F6: 0.32 | G6: 0.32
A7: EBIT | B7: =Inputs!D5 -> 133050 | C7: =C5*C6 -> 141161.81 | D7: =D5*D6 -> 148925.71 | E7: =E5*E6 -> 156372 | F7: =F5*F6 -> 163408.74 | G7: =G5*G6 -> 169945.09
A8: Tax rate | B8: =Inputs!D10 -> 0.15610002 | C8: 0.16 | D8: 0.16 | E8: 0.16 | F8: 0.16 | G8: 0.16
A9: NOPAT = EBIT x (1 - t) | B9: =B7*(1-B8) -> 112280.89 | C9: =C7*(1-C8) -> 118575.92 | D9: =D7*(1-D8) -> 125097.6 | E9: =E7*(1-E8) -> 131352.48 | F9: =F7*(1-F8) -> 137263.34 | G9: =G7*(1-G8) -> 142753.87
A10: D&A % of revenue | B10: =Inputs!D6/Inputs!D4 -> 0.028109313 | C10: 0.028 | D10: 0.028 | E10: 0.028 | F10: 0.028 | G10: 0.028
A11: D&A | B11: =Inputs!D6 -> 11698 | C11: =C5*C10 -> 12351.658 | D11: =D5*D10 -> 13031 | E11: =E5*E10 -> 13682.55 | F11: =F5*F10 -> 14298.264 | G11: =G5*G10 -> 14870.195
A12: Capex % of revenue | B12: =Inputs!D7/Inputs!D4 -> 0.030553079 | C12: 0.03 | D12: 0.03 | E12: 0.03 | F12: 0.03 | G12: 0.03
A13: Capex | B13: =Inputs!D7 -> 12715 | C13: =C5*C12 -> 13233.92 | D13: =D5*D12 -> 13961.785 | E13: =E5*E12 -> 14659.875 | F13: =F5*F12 -> 15319.569 | G13: =G5*G12 -> 15932.352
A14: NWC investment, % of revenue change | C14: 0.05 | D14: 0.05 | E14: 0.05 | F14: 0.05 | G14: 0.05
A15: Increase in NWC (cash outflow) | B15: =-Inputs!D11 -> 25000 | C15: =C14*(C5-B5) -> 1248.483 | D15: =D14*(D5-C5) -> 1213.1093 | E15: =E14*(E5-D5) -> 1163.4821 | F15: =F14*(F5-E5) -> 1099.4906 | G15: =G14*(G5-F5) -> 1021.3046
A16: Unlevered FCF = NOPAT + D&A - capex - increase in NWC | B16: =B9+B11-B13-B15 -> 86263.892 | C16: =C9+C11-C13-C15 -> 116445.18 | D16: =D9+D11-D13-D15 -> 122953.7 | E16: =E9+E11-E13-E15 -> 129211.67 | F16: =F9+F11-F13-F15 -> 135142.54 | G16: =G9+G11-G13-G15 -> 140670.41
A17: Discount period (years, end-of-year) | C17: 1 | D17: 2 | E17: 3 | F17: 4 | G17: 5
A18: Discount factor | C18: =1/(1+WACC!$B$13)^C17 -> 0.91741753 | D18: =1/(1+WACC!$B$13)^D17 -> 0.84165492 | E18: =1/(1+WACC!$B$13)^E17 -> 0.77214897 | F18: =1/(1+WACC!$B$13)^F17 -> 0.708383 | G18: =1/(1+WACC!$B$13)^G17 -> 0.64988298
A19: PV of UFCF | C19: =C16*C18 -> 106828.85 | D19: =D16*D18 -> 103484.59 | E19: =E16*E18 -> 99770.658 | F19: =F16*F18 -> 95732.68 | G19: =G16*G18 -> 91419.306
A21: Valuation
A22: Sum of PV of UFCF | B22: =SUM(C19:G19) -> 497236.08
A23: Terminal growth rate | B23: =Inputs!B39 -> 0.025
A24: WACC | B24: =WACC!B13 -> 0.090016236
A25: Terminal value at FY2030 = UFCF x (1+g) / (WACC - g) | B25: =G16*(1+B23)/(B24-B23) -> 2217710.2
A26: PV of terminal value | B26: =B25*G18 -> 1441252.1
A27: Enterprise value | B27: =B22+B26 -> 1938488.2
A28: Less: net debt (negative = net cash) | B28: =Inputs!D29 -> -33763
A29: Equity value | B29: =B27-B28 -> 1972251.2
A30: Diluted shares (millions) | B30: =Inputs!D30 -> 15004.7
A31: Intrinsic value per share ($) | B31: =B29/B30 -> 131.44223
A32: Terminal value as % of EV | B32: =B26/B27 -> 0.74349285
A33: Reference share price ($) | B33: =Inputs!B38 -> 250
A34: Implied upside / (downside) vs reference price | B34: =B31/B33-1 -> -0.47423109

Sheet Inputs
A1: Apple Inc. (AAPL) - DCF inputs, $ millions unless stated. Blue = hard-coded input from source.
A2: Source: Form 10-K FY2025 (FYE 27 Sep 2025), accession 0000320193-25-000079, filed 2025-10-31; values via SEC XBRL companyfacts.
A3: Income / cash flow | B3: FY2023 | C3: FY2024 | D3: FY2025 | E3: XBRL tag
A4: Revenue | B4: 383285 | C4: 391035 | D4: 416161 | E4: RevenueFromContractWithCustomerExcludingAssessedTax
A5: Operating income (EBIT) | B5: 114301 | C5: 123216 | D5: 133050 | E5: OperatingIncomeLoss
A6: Depreciation & amortization | B6: 11519 | C6: 11445 | D6: 11698 | E6: DepreciationDepletionAndAmortization
A7: Capital expenditure (payments for PP&E) | B7: 10959 | C7: 9447 | D7: 12715 | E7: PaymentsToAcquirePropertyPlantAndEquipment
A8: Pre-tax income | B8: 113736 | C8: 123485 | D8: 132729 | E8: IncomeLossFromContinuingOperationsBefore...Taxes
A9: Income tax expense | B9: 16741 | C9: 29749 | D9: 20719 | E9: IncomeTaxExpenseBenefit
A10: Effective tax rate | B10: =B9/B8 -> 0.14719174 | C10: =C9/C8 -> 0.24091185 | D10: =D9/D8 -> 0.15610002
A11: Cash-flow effect of working capital (+ = inflow) | B11: =-(B13+B14+B15+B16)+(B17+B18) -> -6577 | C11: =-(C13+C14+C15+C16)+(C17+C18) -> 3651 | D11: =-(D13+D14+D15+D16)+(D17+D18) -> -25000 | E11: Derived from rows 13-18; FY2024/FY2025 contain large one-off tax-related swings
A12: Working-capital items (XBRL sign: assets +=increase=cash outflow; liabilities +=increase=cash inflow)
A13: Change in accounts receivable | B13: 1688 | C13: 3788 | D13: 6682 | E13: IncreaseDecreaseInAccountsReceivable
A14: Change in inventories | B14: 1618 | C14: 1046 | D14: -1400 | E14: IncreaseDecreaseInInventories
A15: Change in vendor non-trade receivables | B15: -1271 | C15: 1356 | D15: 347 | E15: IncreaseDecreaseInOtherReceivables
A16: Change in other operating assets | B16: 5684 | C16: 11731 | D16: 9197 | E16: IncreaseDecreaseInOtherOperatingAssets
A17: Change in accounts payable | B17: -1889 | C17: 6020 | D17: 902 | E17: IncreaseDecreaseInAccountsPayable
A18: Change in other operating liabilities | B18: 3031 | C18: 15552 | D18: -11076 | E18: IncreaseDecreaseInOtherOperatingLiabilities
A20: Balance sheet and share data (FY2025 year-end) | D20: FY2025 | E20: XBRL tag
A21: Commercial paper | D21: 7979 | E21: CommercialPaper
A22: Term debt, current | D22: 12350 | E22: LongTermDebtCurrent
A23: Term debt, non-current | D23: 78328 | E23: LongTermDebtNoncurrent
A24: Total debt | D24: =SUM(D21:D23) -> 98657
A25: Cash and cash equivalents | D25: 35934 | E25: CashAndCashEquivalentsAtCarryingValue
A26: Marketable securities, current | D26: 18763 | E26: MarketableSecuritiesCurrent
A27: Marketable securities, non-current | D27: 77723 | E27: MarketableSecuritiesNoncurrent
A28: Total cash and investments | D28: =SUM(D25:D27) -> 132420
A29: Net debt (negative = net cash) | D29: =D24-D28 -> -33763
A30: Diluted weighted-average shares (millions) | D30: 15004.7 | E30: WeightedAverageNumberOfDilutedSharesOutstanding
A31: Shares outstanding at 17 Oct 2025 (millions, info only) | D31: 14776.353 | E31: dei:EntityCommonStockSharesOutstanding
A33: Manager-supplied market inputs (synthetic, fixed for this task) | B33: Value
A34: Risk-free rate | B34: 0.042
A35: Equity risk premium | B35: 0.045
A36: Equity beta | B36: 1.1
A37: Pre-tax cost of debt | B37: 0.04
A38: Reference share price ($, not a live quote) | B38: 250
A39: Terminal growth rate (base) | B39: 0.025

Sheet WACC
A1: WACC build | B1: Value | C1: Note
A2: Risk-free rate | B2: =Inputs!B34 -> 0.042 | C2: Manager notes
A3: Equity risk premium | B3: =Inputs!B35 -> 0.045 | C3: Manager notes
A4: Beta | B4: =Inputs!B36 -> 1.1 | C4: Manager notes
A5: Cost of equity (CAPM) | B5: =B2+B4*B3 -> 0.0915 | C5: Rf + beta x ERP
A6: Pre-tax cost of debt | B6: =Inputs!B37 -> 0.04 | C6: Manager notes
A7: Tax rate | B7: =DCF!C8 -> 0.16 | C7: Projection tax rate
A8: After-tax cost of debt | B8: =B6*(1-B7) -> 0.0336
A9: Market value of equity ($M) | B9: =Inputs!B38*Inputs!D30 -> 3751175 | C9: Reference price x diluted shares
A10: Debt ($M) | B10: =Inputs!D24 -> 98657 | C10: Book value as proxy for market value
A11: Equity weight | B11: =B9/(B9+B10) -> 0.97437369
A12: Debt weight | B12: =B10/(B9+B10) -> 0.025626313
A13: WACC | B13: =B11*B5+B12*B8 -> 0.090016236 | C13: Used in DCF

Sheet Sensitivity
A1: Intrinsic value per share ($): WACC (rows) vs terminal growth (columns)
A4: WACC \ g | B4: 0.015 | C4: 0.02 | D4: 0.025 | E4: 0.03 | F4: 0.035
A5: =WACC!$B$13+(-0.01) -> 0.080016236 | B5: =(NPV($A5,DCF!$C$16:$G$16)+DCF!$G$16*(1+B$4)/($A5-B$4)/(1+$A5)^5-Inputs!$D$29)/Inputs!$D$30 -> 135.89847 | C5: =(NPV($A5,DCF!$C$16:$G$16)+DCF!$G$16*(1+C$4)/($A5-C$4)/(1+$A5)^5-Inputs!$D$29)/Inputs!$D$30 -> 144.72793 | D5: =(NPV($A5,DCF!$C$16:$G$16)+DCF!$G$16*(1+D$4)/($A5-D$4)/(1+$A5)^5-Inputs!$D$29)/Inputs!$D$30 -> 155.16226 | E5: =(NPV($A5,DCF!$C$16:$G$16)+DCF!$G$16*(1+E$4)/($A5-E$4)/(1+$A5)^5-Inputs!$D$29)/Inputs!$D$30 -> 167.68278 | F5: =(NPV($A5,DCF!$C$16:$G$16)+DCF!$G$16*(1+F$4)/($A5-F$4)/(1+$A5)^5-Inputs!$D$29)/Inputs!$D$30 -> 182.98464
A6: =WACC!$B$13+(-0.005) -> 0.085016236 | B6: =(NPV($A6,DCF!$C$16:$G$16)+DCF!$G$16*(1+B$4)/($A6-B$4)/(1+$A6)^5-Inputs!$D$29)/Inputs!$D$30 -> 126.21557 | C6: =(NPV($A6,DCF!$C$16:$G$16)+DCF!$G$16*(1+C$4)/($A6-C$4)/(1+$A6)^5-Inputs!$D$29)/Inputs!$D$30 -> 133.64542 | D6: =(NPV($A6,DCF!$C$16:$G$16)+DCF!$G$16*(1+D$4)/($A6-D$4)/(1+$A6)^5-Inputs!$D$29)/Inputs!$D$30 -> 142.31324 | E6: =(NPV($A6,DCF!$C$16:$G$16)+DCF!$G$16*(1+E$4)/($A6-E$4)/(1+$A6)^5-Inputs!$D$29)/Inputs!$D$30 -> 152.55656 | F6: =(NPV($A6,DCF!$C$16:$G$16)+DCF!$G$16*(1+F$4)/($A6-F$4)/(1+$A6)^5-Inputs!$D$29)/Inputs!$D$30 -> 164.84789
A7: =WACC!$B$13+(0) -> 0.090016236 | B7: =(NPV($A7,DCF!$C$16:$G$16)+DCF!$G$16*(1+B$4)/($A7-B$4)/(1+$A7)^5-Inputs!$D$29)/Inputs!$D$30 -> 117.8257 | C7: =(NPV($A7,DCF!$C$16:$G$16)+DCF!$G$16*(1+C$4)/($A7-C$4)/(1+$A7)^5-Inputs!$D$29)/Inputs!$D$30 -> 124.14777 | D7: =(NPV($A7,DCF!$C$16:$G$16)+DCF!$G$16*(1+D$4)/($A7-D$4)/(1+$A7)^5-Inputs!$D$29)/Inputs!$D$30 -> 131.44223 | E7: =(NPV($A7,DCF!$C$16:$G$16)+DCF!$G$16*(1+E$4)/($A7-E$4)/(1+$A7)^5-Inputs!$D$29)/Inputs!$D$30 -> 139.9521 | F7: =(NPV($A7,DCF!$C$16:$G$16)+DCF!$G$16*(1+F$4)/($A7-F$4)/(1+$A7)^5-Inputs!$D$29)/Inputs!$D$30 -> 150.00876
A8: =WACC!$B$13+(0.005) -> 0.095016236 | B8: =(NPV($A8,DCF!$C$16:$G$16)+DCF!$G$16*(1+B$4)/($A8-B$4)/(1+$A8)^5-Inputs!$D$29)/Inputs!$D$30 -> 110.4864 | C8: =(NPV($A8,DCF!$C$16:$G$16)+DCF!$G$16*(1+C$4)/($A8-C$4)/(1+$A8)^5-Inputs!$D$29)/Inputs!$D$30 -> 115.91803 | D8: =(NPV($A8,DCF!$C$16:$G$16)+DCF!$G$16*(1+D$4)/($A8-D$4)/(1+$A8)^5-Inputs!$D$29)/Inputs!$D$30 -> 122.12542 | E8: =(NPV($A8,DCF!$C$16:$G$16)+DCF!$G$16*(1+E$4)/($A8-E$4)/(1+$A8)^5-Inputs!$D$29)/Inputs!$D$30 -> 129.28756 | F8: =(NPV($A8,DCF!$C$16:$G$16)+DCF!$G$16*(1+F$4)/($A8-F$4)/(1+$A8)^5-Inputs!$D$29)/Inputs!$D$30 -> 137.64306
A9: =WACC!$B$13+(0.01) -> 0.10001624 | B9: =(NPV($A9,DCF!$C$16:$G$16)+DCF!$G$16*(1+B$4)/($A9-B$4)/(1+$A9)^5-Inputs!$D$29)/Inputs!$D$30 -> 104.01229 | C9: =(NPV($A9,DCF!$C$16:$G$16)+DCF!$G$16*(1+C$4)/($A9-C$4)/(1+$A9)^5-Inputs!$D$29)/Inputs!$D$30 -> 108.71847 | D9: =(NPV($A9,DCF!$C$16:$G$16)+DCF!$G$16*(1+D$4)/($A9-D$4)/(1+$A9)^5-Inputs!$D$29)/Inputs!$D$30 -> 114.05202 | E9: =(NPV($A9,DCF!$C$16:$G$16)+DCF!$G$16*(1+E$4)/($A9-E$4)/(1+$A9)^5-Inputs!$D$29)/Inputs!$D$30 -> 120.14731 | F9: =(NPV($A9,DCF!$C$16:$G$16)+DCF!$G$16*(1+F$4)/($A9-F$4)/(1+$A9)^5-Inputs!$D$29)/Inputs!$D$30 -> 127.18012
A11: Check: base cell minus DCF!B31 (should be 0) | B11: =D7-DCF!B31 -> 0

Sheet Assumptions
A1: Assumptions and risks
A2: Revenue growth fades from 6.0% to 4.0% (FY2023-25 CAGR is 4.2%; FY2025 growth was 6.4%). EBIT margin is held at 32.0% (FY2025: 32.0%). Tax is 16% (FY2025 effective rate 15.6%; FY2024's 24.1% was inflated by a one-time tax charge). D&A (2.8%) and capex (3.0%) of revenue sit near FY2025 levels. Working-capital investment is 5% of revenue growth; reported swings (-6.6bn, +3.7bn, -25.0bn) reflect one-off tax items, so they are not extrapolated. Stock-based compensation is treated as a real cost (not added back). Operating leases stay in operating costs and are excluded from debt. Net cash includes marketable securities. Discounting is end-of-year. Risks: supply-chain and sales concentration in Greater China plus tariff exposure; regulatory pressure on App Store and Services economics (EU DMA, US antitrust). Terminal value is most of EV, so WACC and growth matter.
